{
  "class_uid": 4002,
  "activity_id": 1,
  "activity_name": "HTTPsession",
  "time": "2026-04-23T12:00:00Z",
  "status": "Success",
  "status_id": 1,
  "status_detail": "200",
  "severity": "Informational",
  "metadata": {
    "product": {
      "name": "NGINX",
      "vendor_name": "F5"
    },
    "version": "1.3.0"
  },
  "device": {
    "uid": "proxy01",
    "hostname": "proxy01.corp",
    "ip": "10.0.0.5"
  },
  "src_endpoint": {
    "ip": "10.1.2.3",
    "hostname": "client.corp",
    "port": 54321
  },
  "dst_endpoint": {
    "ip": "93.184.216.34",
    "hostname": "example.com",
    "port": 443
  },
  "connection_info": {
    "protocol_name": "TCP",
    "direction": "Outbound"
  },
  "traffic": {
    "bytes": 8421,
    "bytes_in": 7200,
    "bytes_out": 1221
  },
  "url": {
    "url_string": "https://example.com/api/v1/users?id=42",
    "category": "Information Technology"
  },
  "http_request": {
    "version": "HTTP/1.1",
    "http_method": "GET",
    "user_agent": "Mozilla/5.0 (Macintosh; Intel Mac OS X 10_15_7) AppleWebKit/537.36 (KHTML, like Gecko) Chrome/124.0.0.0 Safari/537.36",
    "referrer": "https://example.com/dashboard",
    "args": "id=42"
  },
  "http_response": {
    "code": 200,
    "content_type": "application/json",
    "latency": 142
  },
  "file": {
    "name": "users.json"
  },
  "action": "allow"
}
