{
  "class_uid": 3005,
  "class_name": "User Access Management",
  "category_uid": 3,
  "category_name": "Identity & Access Management",
  "type_uid": 300503,
  "type_name": "User Access Management: Add User to Group",
  "activity_id": 3,
  "activity_name": "UserAddedToGroup",
  "time": "2026-04-23T14:22:10.000Z",
  "severity_id": 1,
  "severity": "Informational",
  "status": "Success",
  "status_id": 1,
  "metadata": {
    "version": "1.3.0",
    "product": {
      "name": "Azure Active Directory",
      "vendor_name": "Microsoft"
    }
  },
  "actor": {
    "user": {
      "name": "admin@contoso.com",
      "uid": "a1b2c3d4-5678-90ab-cdef-1234567890ab",
      "type": "User",
      "type_id": 1
    }
  },
  "user": {
    "name": "jdoe@contoso.com",
    "uid": "b2c3d4e5-6789-01bc-def0-234567890abc",
    "type": "User",
    "type_id": 1
  },
  "group": {
    "name": "Engineering",
    "uid": "g-eng-001",
    "type": "Security"
  },
  "device": {
    "uid": "dc01.contoso.com",
    "hostname": "dc01.contoso.com",
    "ip": "10.0.1.12"
  },
  "src_endpoint": {
    "ip": "203.0.113.45",
    "hostname": "admin-workstation-01"
  },
  "message": "User jdoe@contoso.com was added to group Engineering by admin@contoso.com"
}
